edgen/__init__.py
edgen/__main__.py
edgen/_base_client.py
edgen/_client.py
edgen/_compat.py
edgen/_constants.py
edgen/_exceptions.py
edgen/_files.py
edgen/_models.py
edgen/_module_client.py
edgen/_qs.py
edgen/_resource.py
edgen/_response.py
edgen/_streaming.py
edgen/_types.py
edgen/_version.py
edgen/pagination.py
edgen/py.typed
edgen/version.py
edgen/_extras/__init__.py
edgen/_extras/_common.py
edgen/_extras/numpy_proxy.py
edgen/_extras/pandas_proxy.py
edgen/_utils/__init__.py
edgen/_utils/_logs.py
edgen/_utils/_proxy.py
edgen/_utils/_streams.py
edgen/_utils/_transform.py
edgen/_utils/_typing.py
edgen/_utils/_utils.py
edgen/lib/.keep
edgen/lib/_validators.py
edgen/resources/__init__.py
edgen/resources/audio/__init__.py
edgen/resources/audio/audio.py
edgen/resources/audio/transcriptions.py
edgen/resources/chat/__init__.py
edgen/resources/chat/chat.py
edgen/resources/chat/completions.py
edgen/resources/misc/__init__.py
edgen/resources/misc/misc.py
edgen/types/__init__.py
edgen/types/completion.py
edgen/types/completion_choice.py
edgen/types/completion_create_params.py
edgen/types/completion_usage.py
edgen/types/audio/__init__.py
edgen/types/audio/transcription.py
edgen/types/audio/transcription_create_params.py
edgen/types/chat/__init__.py
edgen/types/chat/chat_completion.py
edgen/types/chat/chat_completion_assistant_message_param.py
edgen/types/chat/chat_completion_chunk.py
edgen/types/chat/chat_completion_content_part_image_param.py
edgen/types/chat/chat_completion_content_part_param.py
edgen/types/chat/chat_completion_content_part_text_param.py
edgen/types/chat/chat_completion_function_call_option_param.py
edgen/types/chat/chat_completion_function_message_param.py
edgen/types/chat/chat_completion_message.py
edgen/types/chat/chat_completion_message_param.py
edgen/types/chat/chat_completion_message_tool_call.py
edgen/types/chat/chat_completion_message_tool_call_param.py
edgen/types/chat/chat_completion_named_tool_choice_param.py
edgen_client-0.1.2.dist-info/METADATA
edgen_client-0.1.2.dist-info/WHEEL
edgen_client-0.1.2.dist-info/licenses/LICENSE
edgen_client-0.1.2.dist-info/RECORD
